{"id":"RID:0111151250224-23","type":"article-journal","author":[{"family":"Cros","given":"RM"},{"family":"Saez","given":"L"},{"family":"Rossello","given":"JA"}],"event-date":{"date-parts":[[2005]]},"issued":{"date-parts":[[2005]]},"collection-title":"Journal of Bryology","container-title":"Journal of Bryology","DOI":"10.1179/174328205X40527","number-of-pages":"4","page":"3-6","page-first":"3","title":"Plagiochasma appendiculatum Lehm. & Lindenb. (Marchantiales, Aytoniaceae), a species new to the European bryophyte flora","URL":"10.1179/174328205X40527","volume":"27"}