{"id":"RID:0111151250226-39","type":"article-journal","author":[{"family":"Mus","given":"M"},{"family":"Saez","given":"L"},{"family":"Rossello","given":"JA"}],"event-date":{"date-parts":[[2000]]},"issued":{"date-parts":[[2000]]},"collection-title":"Taxon","container-title":"Taxon","DOI":"10.2307/1223979","issue":"4","number":"4","number-of-pages":"4","page":"785-788","page-first":"785","title":"Viola barceloi Nyman, V-barceloi L. Chodat and V-suavis var. barceloi O. Bolos & Vigo: too many eponyms or too many taxa?","URL":"10.2307/1223979","volume":"49"}