{"id":"RID:1105180800965-96","type":"article-journal","author":[{"family":"Juan","given":"Ana"},{"family":"Blanca","given":"Gabriel"},{"family":"Cueto","given":"Miguel"},{"family":"Fuentes","given":"Julian"},{"family":"Saez","given":"Llorenc"}],"event-date":{"date-parts":[[2018]]},"issued":{"date-parts":[[2018]]},"collection-title":"Phytotaxa","container-title":"Phytotaxa","DOI":"10.11646/phytotaxa.343.2.3","issue":"2","number":"2","number-of-pages":"12","page":"127-138","page-first":"127","title":"Linaria argillicola (Plantaginaceae), a new species of L. sect. Supinae from the southern Iberian Peninsula","URL":"10.11646/phytotaxa.343.2.3","volume":"343"}