{"id":"RID:1105180800965-92","type":"article-journal","author":[{"family":"Ferrer-Gallego","given":"P. Pablo"},{"family":"Saez","given":"Llorenc"}],"event-date":{"date-parts":[[2018]]},"issued":{"date-parts":[[2018]]},"collection-title":"Taxon","container-title":"Taxon","DOI":"10.12705/674.15","issue":"4","number":"4","number-of-pages":"2","page":"808-809","page-first":"808","title":"(2630) Proposal to conserve the name Allium rotundum (Amaryllidaceae) with a conserved type","URL":"10.12705/674.15","volume":"67"}