{"id":"RID:1223151958656-108","type":"article-journal","author":[{"family":"Yu","given":"WB"},{"family":"Wang","given":"H"},{"family":"Ren","given":"YQ"},{"family":"Li","given":"DZ"}],"event-date":{"date-parts":[[2015]]},"issued":{"date-parts":[[2015]]},"collection-title":"Plant Ecology and Evolution","container-title":"Plant Ecology and Evolution","DOI":"10.5091/plecevo.2015.975","issue":"1","number":"1","number-of-pages":"5","page":"144-148","page-first":"144","title":"Typification of seven Chinese species of Pedicularis (Orobanchaceae) described by Bureau and Franchet with taxonomic notes","URL":"10.5091/plecevo.2015.975","volume":"148"}